{
  "event_message": "📄 Loaded posts: [\n  [ \"#BookishTalks\", \"#SeniorBookworms\" ],\n  [ \"#Nostalgia\", \"#FamilyPhotoAlbum\" ],\n  [ \"#Creativity\", \"#StreetArtVibes\" ],\n  [ \"#Disgust\", \"#Injustice\" ],\n  [ \"#CreativeExpressions\", \"#SeniorArt\" ],\n  [ \"#Ambivalence\", \"#ConflictingFeelings\" ],\n  [ \"#Confusion\", \"#ThoughtLabyrinth\" ],\n  [ \"#Adventure\", \"#SnowPeakDance\" ],\n  [ \"#Blessed\", \"#SupportiveCommunity\" ],\n  [ \"#Reflection\", \"#ParisianDreams\" ],\n  [ \"#Fearful\", \"#SpecterOfTheUnknown\" ],\n  [ \"#Envious\", \"#GildedPrize\" ],\n  [ \"#CityExplore\", \"#HiddenGems\" ],\n  [ \"#Dismissive\", \"#IndifferencePerformance\" ],\n  [ \"#StagePassion\", \"#SeniorTheater\" ],\n  [ \"#Affection\", \"#PositiveVibes\" ],\n  [ \"#Serenity\", \"#MoonlitPeace\" ],\n  [ \"#PaperPlaneExpert\", \"#HighSchoolArt\" ],\n  [ \"#Emotion\", \"#AdeleMelodies\" ],\n  [ \"#SayingGoodbye\", \"#HighSchoolEmotions\" ],\n  [ \"#Contentment\", \"#InnerPeace\" ],\n  [ \"#Colorful\", \"#KatyPerry\" ],\n  [ \"#LifetimeAdventure\", \"#SeniorCuriosity\" ],\n  [ \"#Hopeful\", \"#CanvasOfDreams\" ],\n  [ \"#Captivation\", \"#GladiatorTales\" ],\n  [ \"#Calmness\", \"#PeacefulMind\" ],\n  [ \"#Gratitude\", \"#FamilyLaughter\" ],\n  [ \"#Calmness\", \"#Mindfulness\" ],\n  [ \"#Sadness\", \"#Farewell\" ],\n  [ \"#ArtisticMishaps\", \"#HighSchoolArt\" ],\n  [ \"#Contentment\", \"#SundayMood\" ],\n  [ \"#ArtisticExpression\", \"#HighSchoolCreativity\" ],\n  [ \"#Hypnotic\", \"#ShakiraRhythms\" ],\n  [ \"#Desolation\", \"#UntoldSorrows\" ],\n  [ \"#SportsTriumph\", \"#HighSchoolAthletics\" ],\n  [ \"#Contentment\", \"#TranquilWaters\" ],\n  [ \"#Despair\", \"#DeepDescent\" ],\n  [ \"#Elation\", \"#FriendshipReunion\" ],\n  [ \"#HandstandChallenge\", \"#HighSchoolAthlete\" ],\n  [ \"#CrushFail\", \"#HighSchoolEmbarrassment\" ],\n  [ \"#Playful\", \"#JugglingResponsibilities\" ],\n  [ \"#Playful\", \"#JugglingResponsibilities\" ],\n  [ \"#Anxiety\", \"#Worry\" ],\n  [ \"#BadLuck\", \"#HighSchoolWeather\" ],\n  [ \"#SchoolEvents\", \"#HighSchoolConnectivity\" ],\n  [ \"#Romance\", \"#TimelessCity\" ],\n  [ \"#Overwhelmed\", \"#BouldersOfExhaustion\" ],\n  [ \"#Heartbreak\", \"#CalmAfterStorm\" ],\n  [ \"#SurpriseParty\", \"#HighSchoolCelebration\" ],\n  [ \"#InstrumentLearning\", \"#TeenMusic\" ],\n  [ \"#Grief\", \"#Loss\" ],\n  [ \"#Boredom\", \"#LackOfInterest\" ],\n  [ \"#Bitterness\", \"#IciclesOfResentment\" ],\n  [ \"#Joy\", \"#ComedyShow\" ],\n  [ \"#TalentShow\", \"#HighSchoolEntertainment\" ],\n  [ \"#MagicFail\", \"#HighSchoolMagic\" ],\n  [ \"#FriendshipGoals\", \"#HighSchoolMemories\" ],\n  [ \"#HairExperiment\", \"#HighSchoolStyle\" ],\n  [ \"#Hopeful\", \"#SailorOfDreams\" ],\n  [ \"#RainDance\", \"#HighSchoolJoy\" ],\n  [ \"#Gratitude\", \"#Blessed\" ],\n  [ \"#BookClub\", \"#HighSchoolReads\" ],\n  [ \"#Mesmerizing\", \"#NightDancePerformance\" ],\n  [ \"#WinterMagic\", \"#SnowyLandscapes\" ],\n  [ \"#Despair\", \"#OwnGoal\" ],\n  [ \"#LoveLetterFail\", \"#HighSchoolAwkward\" ],\n  [ \"#Regret\", \"#MissedChances\" ],\n  [ \"#Despair\", \"#Hopeless\" ],\n  [ \"#Dismissive\", \"#ImpenetrableWalls\" ],\n  [ \"#Grief\", \"#SilentTears\" ],\n  [ \"#Art\", \"#PaintingInProgress\" ],\n  [ \"#Travel\", \"#Adventure\" ],\n  [ \"#Enthusiasm\", \"#Creativity\" ],\n  [ \"#Accomplishment\", \"#SunriseHues\" ],\n  [ \"#Compassion\", \"#HolidaySupport\" ],\n  [ \"#Loneliness\", \"#CrashingWaves\" ],\n  [ \"#Envy\", \"#Desire\" ],\n  [ \"#Grief\", \"#Tears\" ],\n  [ \"#Kindness\", \"#LoveStitches\" ],\n  [ \"#Regret\", \"#PastChoices\" ],\n  [ \"#Grief\", \"#EmotionalStorm\" ],\n  [ \"#Nostalgia\", \"#DiaryJourney\" ],\n  [ \"#Coding\", \"#Enthusiasm\" ],\n  [ \"#Jealous\", \"#BloomingAchievements\" ],\n  [ \"#GetawayGoals\", \"#TeenTravel\" ],\n  [ \"#Loneliness\", \"#SolitaryNocturne\" ],\n  [ \"#Gratitude\", \"#MorningCoffee\" ],\n  [ \"#Melancholy\", \"#WistfulYearning\" ],\n  [ \"#Euphoria\", \"#ArianaGrande\" ],\n  [ \"#Pressure\", \"#GolfDefeat\" ],\n  [ \"#Solitude\", \"#ShadowConversation\" ],\n  [ \"#Bitterness\", \"#ResentmentWeb\" ],\n  [ \"#Cooking\", \"#Food\" ],\n  [ \"#Loneliness\", \"#MiragesOfConnection\" ],\n  [ \"#Regret\", \"#PastCurrents\" ],\n  [ \"#Yearning\", \"#DistantWarmth\" ],\n  [ \"#Grateful\", \"#GoldenHues\" ],\n  [ \"#Frustrated\", \"#LabyrinthOfMiscommunication\" ],\n  [ \"#JoyfulReunion\", \"#Friendship\" ],\n  [ \"#Anger\", \"#Argument\" ],\n  ... 632 more items\n]\n",
  "id": "d2fc8634-c200-43ea-bbf2-105a38b856e6",
  "metadata": [
    {
      "boot_time": null,
      "cpu_time_used": null,
      "deployment_id": "xwrdnamcvjytnashyilv_ee23d5dc-34a7-469c-bb35-bc35b29ffacd_18",
      "event_type": "Log",
      "execution_id": "4eb382a5-c62c-48fb-bc5a-dfe3d1095020",
      "function_id": "ee23d5dc-34a7-469c-bb35-bc35b29ffacd",
      "level": "log",
      "memory_used": [],
      "project_ref": "xwrdnamcvjytnashyilv",
      "reason": null,
      "region": "ap-southeast-1",
      "served_by": "supabase-edge-runtime-1.67.3 (compatible with Deno v1.45.2)",
      "timestamp": "2025-05-16T13:22:08.059Z",
      "version": "18"
    }
  ],
  "timestamp": 1747401732000298
}